SuanfaTongguanShouceItchargeFix1/README.md
SuanfaTongguanShouceItchargeFix1/__init__.py
SuanfaTongguanShouceItchargeFix1/__main__.py
SuanfaTongguanShouceItchargeFix1/file.epub
SuanfaTongguanShouceItchargeFix1/index.html
SuanfaTongguanShouceItchargeFix1/css/__init__.py
SuanfaTongguanShouceItchargeFix1/css/annotations.css
SuanfaTongguanShouceItchargeFix1/css/main.css
SuanfaTongguanShouceItchargeFix1/css/normalize.css
SuanfaTongguanShouceItchargeFix1/css/popup.css
SuanfaTongguanShouceItchargeFix1/font/__init__.py
SuanfaTongguanShouceItchargeFix1/font/fontello.eot
SuanfaTongguanShouceItchargeFix1/font/fontello.svg
SuanfaTongguanShouceItchargeFix1/font/fontello.ttf
SuanfaTongguanShouceItchargeFix1/font/fontello.woff
SuanfaTongguanShouceItchargeFix1/img/__init__.py
SuanfaTongguanShouceItchargeFix1/img/annotator-glyph-sprite.png
SuanfaTongguanShouceItchargeFix1/img/annotator-icon-sprite.png
SuanfaTongguanShouceItchargeFix1/img/apple-touch-icon.png
SuanfaTongguanShouceItchargeFix1/img/cancelfullscreen.png
SuanfaTongguanShouceItchargeFix1/img/close.png
SuanfaTongguanShouceItchargeFix1/img/fullscreen.png
SuanfaTongguanShouceItchargeFix1/img/loader.gif
SuanfaTongguanShouceItchargeFix1/img/menu-icon.png
SuanfaTongguanShouceItchargeFix1/img/save.png
SuanfaTongguanShouceItchargeFix1/img/saved.png
SuanfaTongguanShouceItchargeFix1/img/settings-s.png
SuanfaTongguanShouceItchargeFix1/img/settings.png
SuanfaTongguanShouceItchargeFix1/img/star.png
SuanfaTongguanShouceItchargeFix1/js/__init__.py
SuanfaTongguanShouceItchargeFix1/js/epub.js
SuanfaTongguanShouceItchargeFix1/js/epub.min.js
SuanfaTongguanShouceItchargeFix1/js/epub.min.map
SuanfaTongguanShouceItchargeFix1/js/hooks.min.js
SuanfaTongguanShouceItchargeFix1/js/hooks.min.map
SuanfaTongguanShouceItchargeFix1/js/reader.js
SuanfaTongguanShouceItchargeFix1/js/reader.js.map
SuanfaTongguanShouceItchargeFix1/js/reader.min.js
SuanfaTongguanShouceItchargeFix1/js/reader.min.map
SuanfaTongguanShouceItchargeFix1/js/hooks/__init__.py
suanfa_tongguan_shouce_itcharge_fix1-2025.3.25.1.dist-info/METADATA
suanfa_tongguan_shouce_itcharge_fix1-2025.3.25.1.dist-info/WHEEL
suanfa_tongguan_shouce_itcharge_fix1-2025.3.25.1.dist-info/entry_points.txt
suanfa_tongguan_shouce_itcharge_fix1-2025.3.25.1.dist-info/top_level.txt
suanfa_tongguan_shouce_itcharge_fix1-2025.3.25.1.dist-info/RECORD
